starrailcard/__init__.py
starrailcard/client.py
starrailcard/utils.py
starrailcard/src/api/api.py
starrailcard/src/api/enka.py
starrailcard/src/api/enka_parsed.py
starrailcard/src/api/error.py
starrailcard/src/api/hoyolab.py
starrailcard/src/api/hoyolab_parsed.py
starrailcard/src/assets/font/font_hsr.ttf
starrailcard/src/data/avatar.json
starrailcard/src/data/element.json
starrailcard/src/data/keys.json
starrailcard/src/data/paths.json
starrailcard/src/data/relict_sets.json
starrailcard/src/data/stats.json
starrailcard/src/data/weapons.json
starrailcard/src/generator/style_card.py
starrailcard/src/generator/style_profile_phone.py
starrailcard/src/generator/style_relict_score.py
starrailcard/src/generator/style_ticket.py
starrailcard/src/model/StarRailCard.py
starrailcard/src/model/api_mihomo.py
starrailcard/src/model/style.py
starrailcard/src/model/ukrainization_model.py
starrailcard/src/model/utils_model.py
starrailcard/src/showcase/client_api.py
starrailcard/src/showcase/config.py
starrailcard/src/showcase/error.py
starrailcard/src/showcase/parsed_info.py
starrailcard/src/showcase/parsed/Enka.py
starrailcard/src/showcase/parsed/HoYoLab.py
starrailcard/src/tools/cache.py
starrailcard/src/tools/enums.py
starrailcard/src/tools/git.py
starrailcard/src/tools/http.py
starrailcard/src/tools/json_data.py
starrailcard/src/tools/options.py
starrailcard/src/tools/translator.py
starrailcard/src/tools/treePaths.py
starrailcard/src/tools/ukrainization.py
starrailcard/src/tools/calculator/stats.py
starrailcard/src/tools/calculator/src/utils.py
starrailcard/src/tools/calculator/src/assets/max.json
starrailcard/src/tools/calculator/src/assets/relic_id.json
starrailcard/src/tools/calculator/src/assets/rolls.json
starrailcard/src/tools/calculator/src/assets/score.json
starrailcard/src/tools/pill/__init__.py
starrailcard/src/tools/pill/color.py
starrailcard/src/tools/pill/color_control.py
starrailcard/src/tools/pill/diagrama.py
starrailcard/src/tools/pill/gradient_v2.py
starrailcard-2.2.4.dist-info/LICENSE
starrailcard-2.2.4.dist-info/METADATA
starrailcard-2.2.4.dist-info/WHEEL
starrailcard-2.2.4.dist-info/top_level.txt
starrailcard-2.2.4.dist-info/RECORD
